{
  "rotational_count": 10,
  "simple_count": 1,
  "total_frames": 14,
  "frames": [
    {
      "i": 0,
      "anim": "rotational",
      "frame": 0,
      "ox": 32,
      "oy": 23,
      "dir": 0,
      "w": 64,
      "h": 55
    },
    {
      "i": 1,
      "anim": "rotational",
      "frame": 0,
      "ox": 32,
      "oy": 22,
      "dir": 1,
      "w": 64,
      "h": 54
    },
    {
      "i": 2,
      "anim": "rotational",
      "frame": 0,
      "ox": 32,
      "oy": 14,
      "dir": 2,
      "w": 64,
      "h": 46
    },
    {
      "i": 3,
      "anim": "rotational",
      "frame": 0,
      "ox": 32,
      "oy": 14,
      "dir": 3,
      "w": 63,
      "h": 54
    },
    {
      "i": 4,
      "anim": "rotational",
      "frame": 0,
      "ox": 32,
      "oy": 18,
      "dir": 4,
      "w": 63,
      "h": 58
    },
    {
      "i": 5,
      "anim": "rotational",
      "frame": 0,
      "ox": 32,
      "oy": 30,
      "dir": 5,
      "w": 64,
      "h": 62
    },
    {
      "i": 6,
      "anim": "rotational",
      "frame": 0,
      "ox": 32,
      "oy": 28,
      "dir": 6,
      "w": 64,
      "h": 60
    },
    {
      "i": 7,
      "anim": "rotational",
      "frame": 0,
      "ox": 32,
      "oy": 30,
      "dir": 7,
      "w": 64,
      "h": 62
    },
    {
      "i": 8,
      "anim": "rotational",
      "frame": 0,
      "ox": 32,
      "oy": 27,
      "dir": 8,
      "w": 63,
      "h": 67
    },
    {
      "i": 9,
      "anim": "rotational",
      "frame": 0,
      "ox": 32,
      "oy": 32,
      "dir": 9,
      "w": 64,
      "h": 72
    },
    {
      "i": 10,
      "anim": "simple",
      "frame": 0,
      "ox": 4294967293,
      "oy": 4294967288,
      "idx": 0,
      "w": 24,
      "h": 20
    },
    {
      "i": 11,
      "anim": "simple",
      "frame": 1,
      "ox": 4294967293,
      "oy": 4294967288,
      "idx": 0,
      "w": 24,
      "h": 20
    },
    {
      "i": 12,
      "anim": "simple",
      "frame": 2,
      "ox": 4294967293,
      "oy": 4294967289,
      "idx": 0,
      "w": 24,
      "h": 21
    },
    {
      "i": 13,
      "anim": "simple",
      "frame": 3,
      "ox": 4294967293,
      "oy": 4294967288,
      "idx": 0,
      "w": 24,
      "h": 20
    }
  ]
}